zinnia_wymeditor/__init__.py
zinnia_wymeditor/admin.py
zinnia_wymeditor/tests.py
zinnia_wymeditor/static/zinnia_wymeditor/css/wymeditor_styles.css
zinnia_wymeditor/static/zinnia_wymeditor/js/jquery.min.js
zinnia_wymeditor/static/zinnia_wymeditor/js/wymeditor/jquery.wymeditor.js
zinnia_wymeditor/static/zinnia_wymeditor/js/wymeditor/jquery.wymeditor.min.js
zinnia_wymeditor/static/zinnia_wymeditor/js/wymeditor/jquery.wymeditor.pack.js
zinnia_wymeditor/static/zinnia_wymeditor/js/wymeditor/iframe/default/lbl-article.png
zinnia_wymeditor/static/zinnia_wymeditor/js/wymeditor/iframe/default/lbl-aside.png
zinnia_wymeditor/static/zinnia_wymeditor/js/wymeditor/iframe/default/lbl-blockquote.png
zinnia_wymeditor/static/zinnia_wymeditor/js/wymeditor/iframe/default/lbl-command.png
zinnia_wymeditor/static/zinnia_wymeditor/js/wymeditor/iframe/default/lbl-details.png
zinnia_wymeditor/static/zinnia_wymeditor/js/wymeditor/iframe/default/lbl-figcaption.png
zinnia_wymeditor/static/zinnia_wymeditor/js/wymeditor/iframe/default/lbl-figure.png
zinnia_wymeditor/static/zinnia_wymeditor/js/wymeditor/iframe/default/lbl-footer.png
zinnia_wymeditor/static/zinnia_wymeditor/js/wymeditor/iframe/default/lbl-h1.png
zinnia_wymeditor/static/zinnia_wymeditor/js/wymeditor/iframe/default/lbl-h2.png
zinnia_wymeditor/static/zinnia_wymeditor/js/wymeditor/iframe/default/lbl-h3.png
zinnia_wymeditor/static/zinnia_wymeditor/js/wymeditor/iframe/default/lbl-h4.png
zinnia_wymeditor/static/zinnia_wymeditor/js/wymeditor/iframe/default/lbl-h5.png
zinnia_wymeditor/static/zinnia_wymeditor/js/wymeditor/iframe/default/lbl-h6.png
zinnia_wymeditor/static/zinnia_wymeditor/js/wymeditor/iframe/default/lbl-header.png
zinnia_wymeditor/static/zinnia_wymeditor/js/wymeditor/iframe/default/lbl-hgroup.png
zinnia_wymeditor/static/zinnia_wymeditor/js/wymeditor/iframe/default/lbl-mark.png
zinnia_wymeditor/static/zinnia_wymeditor/js/wymeditor/iframe/default/lbl-meter.png
zinnia_wysiwyg_wymeditor-1.2.dist-info/DESCRIPTION.rst
zinnia_wysiwyg_wymeditor-1.2.dist-info/METADATA
zinnia_wysiwyg_wymeditor-1.2.dist-info/RECORD
zinnia_wysiwyg_wymeditor-1.2.dist-info/WHEEL
zinnia_wysiwyg_wymeditor-1.2.dist-info/metadata.json
zinnia_wysiwyg_wymeditor-1.2.dist-info/top_level.txt
